atsge/SGEJobSubmitter.py
atsge/__init__.py
atsge/build_parallel.py
atsge/run.py
atsge-0.2.1.dist-info/LICENSE
atsge-0.2.1.dist-info/METADATA
atsge-0.2.1.dist-info/WHEEL
atsge-0.2.1.dist-info/top_level.txt
atsge-0.2.1.dist-info/RECORD
