Metadata-Version: 2.1
Name: atsge
Version: 0.2.1
Summary: SGE batch job submission with AlphaTwirl
Home-page: https://github.com/shane-breeze/atsge
Author: Shane Breeze
Author-email: sdb15@ic.ac.uk
License: UNKNOWN
Platform: UNKNOWN
Classifier: Programming Language :: Python :: 2
Classifier: Programming Language :: Python :: 3
Classifier: License :: OSI Approved :: MIT License
Classifier: Operating System :: OS Independent
Classifier: Topic :: Software Development :: Libraries :: Python Modules
Classifier: Topic :: Utilities
Classifier: Development Status :: 3 - Alpha
Requires-Dist: alphatwirl (>=0.25.2)
Requires-Dist: atpbar (>=1.0.3)
